
[
  {
    "id": "tge-1",
    "name": "CryptoQuest",
    "tgeDate": "2025-06-15",
    "roadmapScore": 8.4,
    "moralityIndex": 7.9,
    "socialEngagement": 9.2,
    "totalScore": 8.5,
    "tags": ["GameFi", "P2E", "Metaverse"],
    "scoreHistory": [
      { "date": "2025-01-01", "roadmapScore": 6.5, "moralityIndex": 6.8, "socialEngagement": 7.2, "totalScore": 6.8 },
      { "date": "2025-02-01", "roadmapScore": 7.2, "moralityIndex": 7.1, "socialEngagement": 7.8, "totalScore": 7.4 },
      { "date": "2025-03-01", "roadmapScore": 7.8, "moralityIndex": 7.5, "socialEngagement": 8.4, "totalScore": 7.9 },
      { "date": "2025-04-01", "roadmapScore": 8.1, "moralityIndex": 7.7, "socialEngagement": 8.9, "totalScore": 8.2 },
      { "date": "2025-05-01", "roadmapScore": 8.4, "moralityIndex": 7.9, "socialEngagement": 9.2, "totalScore": 8.5 }
    ]
  },
  {
    "id": "tge-2",
    "name": "DeFiNexus",
    "tgeDate": "2025-06-22",
    "roadmapScore": 9.1,
    "moralityIndex": 8.5,
    "socialEngagement": 7.8,
    "totalScore": 8.6,
    "tags": ["DeFi", "Lending", "Yield"],
    "scoreHistory": [
      { "date": "2025-01-01", "roadmapScore": 7.8, "moralityIndex": 7.2, "socialEngagement": 6.1, "totalScore": 7.1 },
      { "date": "2025-02-01", "roadmapScore": 8.3, "moralityIndex": 7.8, "socialEngagement": 6.8, "totalScore": 7.7 },
      { "date": "2025-03-01", "roadmapScore": 8.7, "moralityIndex": 8.2, "socialEngagement": 7.2, "totalScore": 8.1 },
      { "date": "2025-04-01", "roadmapScore": 8.9, "moralityIndex": 8.4, "socialEngagement": 7.5, "totalScore": 8.3 },
      { "date": "2025-05-01", "roadmapScore": 9.1, "moralityIndex": 8.5, "socialEngagement": 7.8, "totalScore": 8.6 }
    ]
  },
  {
    "id": "tge-3",
    "name": "MetaRealms",
    "tgeDate": "2025-07-05",
    "roadmapScore": 7.6,
    "moralityIndex": 8.2,
    "socialEngagement": 8.7,
    "totalScore": 8.1,
    "tags": ["GameFi", "NFT", "Social"],
    "scoreHistory": [
      { "date": "2025-01-01", "roadmapScore": 6.2, "moralityIndex": 7.5, "socialEngagement": 7.1, "totalScore": 6.9 },
      { "date": "2025-02-01", "roadmapScore": 6.8, "moralityIndex": 7.8, "socialEngagement": 7.8, "totalScore": 7.4 },
      { "date": "2025-03-01", "roadmapScore": 7.2, "moralityIndex": 8.0, "socialEngagement": 8.2, "totalScore": 7.8 },
      { "date": "2025-04-01", "roadmapScore": 7.4, "moralityIndex": 8.1, "socialEngagement": 8.5, "totalScore": 8.0 },
      { "date": "2025-05-01", "roadmapScore": 7.6, "moralityIndex": 8.2, "socialEngagement": 8.7, "totalScore": 8.1 }
    ]
  },
  {
    "id": "tge-4",
    "name": "TONBridge",
    "tgeDate": "2025-07-12",
    "roadmapScore": 9.5,
    "moralityIndex": 9.2,
    "socialEngagement": 8.9,
    "totalScore": 9.2,
    "tags": ["Infrastructure", "Bridge", "DeFi"],
    "scoreHistory": [
      { "date": "2025-01-01", "roadmapScore": 8.2, "moralityIndex": 8.1, "socialEngagement": 7.5, "totalScore": 8.0 },
      { "date": "2025-02-01", "roadmapScore": 8.7, "moralityIndex": 8.6, "socialEngagement": 8.0, "totalScore": 8.5 },
      { "date": "2025-03-01", "roadmapScore": 9.1, "moralityIndex": 8.9, "socialEngagement": 8.4, "totalScore": 8.8 },
      { "date": "2025-04-01", "roadmapScore": 9.3, "moralityIndex": 9.0, "socialEngagement": 8.6, "totalScore": 9.0 },
      { "date": "2025-05-01", "roadmapScore": 9.5, "moralityIndex": 9.2, "socialEngagement": 8.9, "totalScore": 9.2 }
    ]
  },
  {
    "id": "tge-5",
    "name": "SocialFi",
    "tgeDate": "2025-07-18",
    "roadmapScore": 8.2,
    "moralityIndex": 7.6,
    "socialEngagement": 9.4,
    "totalScore": 8.4,
    "tags": ["Social", "Creator", "Content"],
    "scoreHistory": [
      { "date": "2025-01-01", "roadmapScore": 6.8, "moralityIndex": 6.5, "socialEngagement": 7.8, "totalScore": 7.0 },
      { "date": "2025-02-01", "roadmapScore": 7.3, "moralityIndex": 6.9, "socialEngagement": 8.4, "totalScore": 7.5 },
      { "date": "2025-03-01", "roadmapScore": 7.8, "moralityIndex": 7.2, "socialEngagement": 8.9, "totalScore": 8.0 },
      { "date": "2025-04-01", "roadmapScore": 8.0, "moralityIndex": 7.4, "socialEngagement": 9.2, "totalScore": 8.2 },
      { "date": "2025-05-01", "roadmapScore": 8.2, "moralityIndex": 7.6, "socialEngagement": 9.4, "totalScore": 8.4 }
    ]
  },
  {
    "id": "tge-6",
    "name": "TerraForge",
    "tgeDate": "2025-07-25",
    "roadmapScore": 7.8,
    "moralityIndex": 8.0,
    "socialEngagement": 7.5,
    "totalScore": 7.8,
    "tags": ["GameFi", "Strategy", "T2E"],
    "scoreHistory": [
      { "date": "2025-01-01", "roadmapScore": 6.0, "moralityIndex": 6.8, "socialEngagement": 6.2, "totalScore": 6.3 },
      { "date": "2025-02-01", "roadmapScore": 6.7, "moralityIndex": 7.2, "socialEngagement": 6.7, "totalScore": 6.9 },
      { "date": "2025-03-01", "roadmapScore": 7.2, "moralityIndex": 7.6, "socialEngagement": 7.0, "totalScore": 7.3 },
      { "date": "2025-04-01", "roadmapScore": 7.5, "moralityIndex": 7.8, "socialEngagement": 7.3, "totalScore": 7.5 },
      { "date": "2025-05-01", "roadmapScore": 7.8, "moralityIndex": 8.0, "socialEngagement": 7.5, "totalScore": 7.8 }
    ]
  },
  {
    "id": "tge-7",
    "name": "AI Tokens",
    "tgeDate": "2025-08-02",
    "roadmapScore": 9.3,
    "moralityIndex": 8.7,
    "socialEngagement": 8.4,
    "totalScore": 8.9,
    "tags": ["AI", "Data", "Utility"],
    "scoreHistory": [
      { "date": "2025-01-01", "roadmapScore": 7.5, "moralityIndex": 7.2, "socialEngagement": 6.8, "totalScore": 7.2 },
      { "date": "2025-02-01", "roadmapScore": 8.2, "moralityIndex": 7.8, "socialEngagement": 7.4, "totalScore": 7.8 },
      { "date": "2025-03-01", "roadmapScore": 8.7, "moralityIndex": 8.3, "socialEngagement": 7.9, "totalScore": 8.3 },
      { "date": "2025-04-01", "roadmapScore": 9.0, "moralityIndex": 8.5, "socialEngagement": 8.2, "totalScore": 8.6 },
      { "date": "2025-05-01", "roadmapScore": 9.3, "moralityIndex": 8.7, "socialEngagement": 8.4, "totalScore": 8.9 }
    ]
  },
  {
    "id": "tge-8",
    "name": "PrivacyShield",
    "tgeDate": "2025-08-09",
    "roadmapScore": 8.9,
    "moralityIndex": 9.1,
    "socialEngagement": 7.2,
    "totalScore": 8.5,
    "tags": ["Privacy", "Security", "Infrastructure"],
    "scoreHistory": [
      { "date": "2025-01-01", "roadmapScore": 7.2, "moralityIndex": 8.0, "socialEngagement": 5.8, "totalScore": 7.0 },
      { "date": "2025-02-01", "roadmapScore": 7.9, "moralityIndex": 8.5, "socialEngagement": 6.2, "totalScore": 7.5 },
      { "date": "2025-03-01", "roadmapScore": 8.4, "moralityIndex": 8.8, "socialEngagement": 6.6, "totalScore": 8.0 },
      { "date": "2025-04-01", "roadmapScore": 8.7, "moralityIndex": 9.0, "socialEngagement": 6.9, "totalScore": 8.3 },
      { "date": "2025-05-01", "roadmapScore": 8.9, "moralityIndex": 9.1, "socialEngagement": 7.2, "totalScore": 8.5 }
    ]
  },
  {
    "id": "tge-9",
    "name": "TONPay",
    "tgeDate": "2025-08-15",
    "roadmapScore": 8.7,
    "moralityIndex": 8.3,
    "socialEngagement": 8.8,
    "totalScore": 8.6,
    "tags": ["Payments", "DeFi", "Utility"],
    "scoreHistory": [
      { "date": "2025-01-01", "roadmapScore": 7.0, "moralityIndex": 6.9, "socialEngagement": 7.2, "totalScore": 7.0 },
      { "date": "2025-02-01", "roadmapScore": 7.7, "moralityIndex": 7.4, "socialEngagement": 7.8, "totalScore": 7.6 },
      { "date": "2025-03-01", "roadmapScore": 8.2, "moralityIndex": 7.9, "socialEngagement": 8.3, "totalScore": 8.1 },
      { "date": "2025-04-01", "roadmapScore": 8.5, "moralityIndex": 8.1, "socialEngagement": 8.6, "totalScore": 8.4 },
      { "date": "2025-05-01", "roadmapScore": 8.7, "moralityIndex": 8.3, "socialEngagement": 8.8, "totalScore": 8.6 }
    ]
  },
  {
    "id": "tge-10",
    "name": "QuantumDAO",
    "tgeDate": "2025-08-22",
    "roadmapScore": 9.0,
    "moralityIndex": 8.5,
    "socialEngagement": 9.0,
    "totalScore": 8.8,
    "tags": ["DAO", "Governance", "DeFi"],
    "scoreHistory": [
      { "date": "2025-01-01", "roadmapScore": 7.4, "moralityIndex": 7.1, "socialEngagement": 7.5, "totalScore": 7.3 },
      { "date": "2025-02-01", "roadmapScore": 8.0, "moralityIndex": 7.7, "socialEngagement": 8.1, "totalScore": 7.9 },
      { "date": "2025-03-01", "roadmapScore": 8.5, "moralityIndex": 8.1, "socialEngagement": 8.5, "totalScore": 8.4 },
      { "date": "2025-04-01", "roadmapScore": 8.8, "moralityIndex": 8.3, "socialEngagement": 8.7, "totalScore": 8.6 },
      { "date": "2025-05-01", "roadmapScore": 9.0, "moralityIndex": 8.5, "socialEngagement": 9.0, "totalScore": 8.8 }
    ]
  }
]